{
    "example_source": [
        "▁我还",
        "澄清",
        "了",
        "在该",
        "会议上",
        "提出的",
        "若干",
        "事项",
        "。"
    ],
    "example_target": [
        "<s>",
        "▁i",
        "▁was",
        "▁able",
        "▁to",
        "▁provide",
        "▁clarification",
        "▁on",
        "▁some",
        "▁of",
        "▁the",
        "▁matters",
        "▁which",
        "▁were",
        "▁raised",
        "▁at",
        "▁that",
        "▁meeting",
        ".",
        "</s>"
    ],
    "hypotheses": [
        {
            "hypothesis": [
                "▁i",
                "▁also",
                "▁clarify",
                "▁the",
                "▁number",
                "▁of",
                "▁issues",
                "▁in",
                "▁the",
                "▁conference",
                "."
            ],
            "score": -10.44749641418457
        },
        {
            "hypothesis": [
                "▁i",
                "▁also",
                "▁clarified",
                "▁the",
                "▁number",
                "▁of",
                "▁issues",
                "▁in",
                "▁the",
                "▁conference",
                "."
            ],
            "score": -10.455451965332031
        },
        {
            "hypothesis": [
                "▁i",
                "▁also",
                "▁clarify",
                "▁the",
                "▁number",
                "▁of",
                "▁issues",
                "▁in",
                "▁the",
                "▁meeting",
                "."
            ],
            "score": -11.210054397583008
        },
        {
            "hypothesis": [
                "▁i",
                "▁also",
                "▁clarified",
                "▁the",
                "▁number",
                "▁of",
                "▁issues",
                "▁in",
                "▁the",
                "▁meeting",
                "."
            ],
            "score": -11.247309684753418
        },
        {
            "hypothesis": [
                "▁i",
                "▁have",
                "▁also",
                "▁clarified",
                "▁the",
                "▁number",
                "▁of",
                "▁issues",
                "▁in",
                "▁the",
                "▁conference",
                "."
            ],
            "score": -11.393338203430176
        },
        {
            "hypothesis": [
                "▁i",
                "▁have",
                "▁also",
                "▁clarified",
                "▁a",
                "▁number",
                "▁of",
                "▁issues",
                "▁in",
                "▁the",
                "▁conference",
                "."
            ],
            "score": -11.49484920501709
        },
        {
            "hypothesis": [
                "▁i",
                "▁have",
                "▁also",
                "▁clarified",
                "▁a",
                "▁number",
                "▁of",
                "▁questions",
                "▁in",
                "▁the",
                "▁conference",
                "."
            ],
            "score": -11.55512523651123
        },
        {
            "hypothesis": [
                "▁i",
                "▁have",
                "▁also",
                "▁clarified",
                "▁a",
                "▁number",
                "▁of",
                "▁questions",
                "▁in",
                "▁the",
                "▁meeting",
                "."
            ],
            "score": -12.122257232666016
        },
        {
            "hypothesis": [
                "▁i",
                "▁have",
                "▁also",
                "▁clarified",
                "▁a",
                "▁number",
                "▁of",
                "▁issues",
                "▁in",
                "▁the",
                "▁meeting",
                "."
            ],
            "score": -12.140645027160645
        },
        {
            "hypothesis": [
                "▁i",
                "▁also",
                "▁clarify",
                "▁the",
                "▁number",
                "▁of",
                "▁issues",
                "▁in",
                "▁the",
                "▁conference",
                "▁on",
                "▁the",
                "▁meeting",
                "."
            ],
            "score": -13.866809844970703
        }
    ],
    "diagnostic_info": "eyJ0IjogIjIwMjQtMDctMjNUMDg6MjE6MTcuNTMwOTU3IiwgImgiOiAiYmxkLXNlcnZlciIsICJ1IjogInpoYW5nbXgifQ=="
}